[null,{"id":1,"autoRemovalTiming":0,"chanceByDamage":100,"iconIndex":1,"maxTurns":1,"message1":"%1倒下了！","message2":"%1打倒了！","message3":"","message4":"%1站起来了！","minTurns":1,"motion":3,"name":"战斗不能","note":"状态1号在HP0时附加。","overlay":0,"priority":100,"releaseByDamage":false,"removeAtBattleEnd":false,"removeByDamage":false,"removeByRestriction":false,"removeByWalking":false,"restriction":4,"stepsToRemove":100,"traits":[{"code":23,"dataId":9,"value":0}],"messageType":1},{"id":2,"autoRemovalTiming":2,"chanceByDamage":100,"iconIndex":0,"maxTurns":1,"message1":"","message2":"","message3":"","message4":"","minTurns":1,"motion":0,"name":"防御","note":"","overlay":0,"priority":0,"removeAtBattleEnd":true,"removeByDamage":false,"removeByRestriction":true,"removeByWalking":false,"restriction":0,"stepsToRemove":100,"traits":[{"code":62,"dataId":1,"value":0}],"messageType":1},{"id":3,"autoRemovalTiming":0,"chanceByDamage":100,"iconIndex":0,"maxTurns":1,"message1":"","message2":"","message3":"","message4":"","minTurns":1,"motion":0,"name":"不死身","note":"","overlay":0,"priority":0,"removeAtBattleEnd":true,"removeByDamage":false,"removeByRestriction":false,"removeByWalking":false,"restriction":0,"stepsToRemove":100,"traits":[{"code":14,"dataId":1,"value":0}],"messageType":1},{"id":4,"autoRemovalTiming":0,"chanceByDamage":100,"iconIndex":2,"maxTurns":1,"message1":"%1中了毒！","message2":"%1你对敌人下了毒！","message3":"","message4":"%1敌人的中毒状态解除了！","minTurns":1,"motion":1,"overlay":1,"name":"毒","note":"","priority":50,"releaseByDamage":false,"removeAtBattleEnd":false,"removeByDamage":false,"removeByRestriction":false,"removeByWalking":false,"restriction":0,"stepsToRemove":100,"traits":[{"code":22,"dataId":7,"value":-0.1}],"messageType":1},{"id":5,"autoRemovalTiming":1,"chanceByDamage":100,"iconIndex":3,"maxTurns":5,"message1":"%1被封闭在黑暗中！","message2":"%1你将敌人封闭在黑暗中！","message3":"","message4":"%1敌人的封闭状态解除了！","minTurns":3,"motion":1,"name":"封闭","note":"","overlay":2,"priority":60,"releaseByDamage":false,"removeAtBattleEnd":true,"removeByDamage":false,"removeByRestriction":false,"removeByWalking":false,"restriction":0,"stepsToRemove":100,"traits":[{"code":22,"dataId":0,"value":-0.5}],"messageType":1},{"id":6,"autoRemovalTiming":1,"chanceByDamage":100,"iconIndex":4,"maxTurns":5,"message1":"%1沉默了！","message2":"%1你让敌人沉默了！","message3":"","message4":"%1敌人的沉默状态解除了！","minTurns":3,"motion":1,"name":"沉默","note":"","overlay":3,"priority":65,"releaseByDamage":false,"removeAtBattleEnd":true,"removeByDamage":false,"removeByRestriction":false,"removeByWalking":false,"restriction":0,"stepsToRemove":100,"traits":[{"code":42,"dataId":1,"value":0}],"messageType":1},{"id":7,"autoRemovalTiming":1,"chanceByDamage":50,"iconIndex":5,"maxTurns":4,"message1":"%1激昂！","message2":"%1让他激昂！","message3":"","message4":"%1回神！","minTurns":2,"motion":1,"name":"激动","note":"","overlay":4,"priority":70,"releaseByDamage":false,"removeAtBattleEnd":true,"removeByDamage":true,"removeByRestriction":false,"removeByWalking":false,"restriction":1,"stepsToRemove":100,"traits":[],"messageType":1},{"id":8,"autoRemovalTiming":1,"chanceByDamage":50,"iconIndex":6,"maxTurns":4,"message1":"%1混乱！","message2":"%1让他混乱！","message3":"","message4":"%1回神！","minTurns":2,"motion":1,"name":"混乱","note":"","overlay":5,"priority":75,"releaseByDamage":false,"removeAtBattleEnd":true,"removeByDamage":true,"removeByRestriction":false,"removeByWalking":false,"restriction":2,"stepsToRemove":100,"traits":[],"messageType":1},{"id":9,"autoRemovalTiming":1,"chanceByDamage":50,"iconIndex":7,"maxTurns":4,"message1":"%1魅惑！","message2":"%1让他魅惑！","message3":"","message4":"%1回神！","minTurns":2,"motion":1,"name":"魅惑","note":"","overlay":6,"priority":80,"releaseByDamage":false,"removeAtBattleEnd":true,"removeByDamage":true,"removeByRestriction":false,"removeByWalking":false,"restriction":3,"stepsToRemove":100,"traits":[],"messageType":1},{"id":10,"autoRemovalTiming":1,"chanceByDamage":100,"iconIndex":8,"maxTurns":5,"message1":"%1睡着！","message2":"%1让他睡着！","message3":"%1睡着。","message4":"%1醒来！","minTurns":3,"motion":2,"name":"睡眠","note":"","overlay":7,"priority":90,"releaseByDamage":true,"removeAtBattleEnd":true,"removeByDamage":true,"removeByRestriction":false,"removeByWalking":false,"restriction":4,"stepsToRemove":100,"traits":[{"code":22,"dataId":1,"value":-1}],"messageType":1},{"id":11,"autoRemovalTiming":2,"chanceByDamage":100,"traits":[{"code":22,"dataId":1,"value":-1}],"iconIndex":28,"maxTurns":3,"message1":"%1冻住不能动！","message2":"%1让他冰结！","message3":"%1冻住不能动！","message4":"%1的冰结解除了！","minTurns":2,"motion":2,"name":"冰结","note":"","overlay":0,"priority":95,"removeAtBattleEnd":true,"removeByDamage":false,"removeByRestriction":false,"removeByWalking":false,"restriction":4,"stepsToRemove":100,"messageType":1},{"id":12,"autoRemovalTiming":2,"chanceByDamage":100,"traits":[{"code":22,"dataId":1,"value":-1}],"iconIndex":9,"maxTurns":3,"message1":"%1麻痹不能动！","message2":"%1让他麻痹！","message3":"%1身体麻痹不能动！","message4":"%1的麻痹解除了！","minTurns":3,"motion":2,"name":"麻痹","note":"","overlay":8,"priority":95,"removeAtBattleEnd":true,"removeByDamage":false,"removeByRestriction":false,"removeByWalking":false,"restriction":4,"stepsToRemove":100,"messageType":1},{"id":13,"autoRemovalTiming":2,"chanceByDamage":100,"traits":[{"code":22,"dataId":1,"value":-1}],"iconIndex":9,"maxTurns":2,"message1":"%1敌人失去平衡！","message2":"%1敌人失去平衡！","message3":"%1敌人失去平衡……","message4":"%1敌人恢复平衡！","minTurns":1,"motion":1,"name":"晕眩","note":"","overlay":10,"priority":90,"removeAtBattleEnd":true,"removeByDamage":false,"removeByRestriction":false,"removeByWalking":false,"restriction":4,"stepsToRemove":100,"messageType":1},{"id":14,"autoRemovalTiming":2,"chanceByDamage":100,"iconIndex":10,"maxTurns":5,"message1":"%1敌人中咒了！","message2":"%1你诅咒敌人！","message3":"","message4":"%1敌人的诅咒解除了！","minTurns":4,"motion":1,"overlay":0,"name":"诅咒","note":"","priority":60,"releaseByDamage":false,"removeAtBattleEnd":true,"removeByDamage":false,"removeByRestriction":false,"removeByWalking":false,"restriction":0,"stepsToRemove":100,"traits":[{"code":22,"dataId":9,"value":-0.1},{"code":21,"dataId":2,"value":0.8},{"code":21,"dataId":3,"value":0.8},{"code":21,"dataId":4,"value":0.8},{"code":21,"dataId":5,"value":0.8},{"code":21,"dataId":6,"value":0.8},{"code":21,"dataId":7,"value":0.8}],"messageType":1},{"id":15,"autoRemovalTiming":2,"chanceByDamage":100,"traits":[{"code":22,"dataId":7,"value":0.1}],"iconIndex":72,"maxTurns":6,"message1":"","message2":"","message3":"","message4":"","minTurns":6,"motion":0,"name":"HP再生","note":"","overlay":0,"priority":40,"removeAtBattleEnd":true,"removeByDamage":false,"removeByRestriction":false,"removeByWalking":false,"restriction":0,"stepsToRemove":100,"messageType":1},{"id":16,"autoRemovalTiming":2,"chanceByDamage":100,"traits":[{"code":22,"dataId":8,"value":0.1}],"iconIndex":72,"maxTurns":4,"message1":"","message2":"","message3":"","message4":"","minTurns":4,"motion":0,"name":"MP再生","note":"","overlay":0,"priority":40,"removeAtBattleEnd":true,"removeByDamage":false,"removeByRestriction":false,"removeByWalking":false,"restriction":0,"stepsToRemove":100,"messageType":1},{"id":17,"autoRemovalTiming":2,"chanceByDamage":100,"traits":[{"code":22,"dataId":9,"value":0.1}],"iconIndex":72,"maxTurns":4,"message1":"","message2":"","message3":"","message4":"","minTurns":4,"motion":0,"name":"TP再生","note":"","overlay":0,"priority":40,"removeAtBattleEnd":true,"removeByDamage":false,"removeByRestriction":false,"removeByWalking":false,"restriction":0,"stepsToRemove":100,"messageType":1},{"id":18,"autoRemovalTiming":2,"chanceByDamage":100,"traits":[{"code":22,"dataId":5,"value":1}],"iconIndex":93,"maxTurns":3,"message1":"%1敌人进入魔法反射状态！","message2":"%1敌人进入魔法反射状态！","message3":"","message4":"%1敌人的魔法反射解除了！","minTurns":3,"motion":0,"name":"魔法反射","note":"","overlay":0,"priority":40,"removeAtBattleEnd":true,"removeByDamage":false,"removeByRestriction":false,"removeByWalking":false,"restriction":0,"stepsToRemove":100,"messageType":1},{"id":19,"autoRemovalTiming":2,"chanceByDamage":100,"traits":[{"code":62,"dataId":2,"value":1}],"iconIndex":81,"maxTurns":1,"message1":"","message2":"","message3":"","message4":"","minTurns":1,"motion":0,"name":"掩护","note":"","overlay":0,"priority":40,"removeAtBattleEnd":true,"removeByDamage":false,"removeByRestriction":true,"removeByWalking":false,"restriction":0,"stepsToRemove":100,"messageType":1},{"id":20,"autoRemovalTiming":2,"chanceByDamage":100,"traits":[{"code":23,"dataId":0,"value":9}],"iconIndex":76,"maxTurns":5,"message1":"%1你容易成为被狙击的目标！","message2":"","message3":"","message4":"","minTurns":5,"motion":0,"name":"挑衅","note":"","overlay":0,"priority":40,"removeAtBattleEnd":true,"removeByDamage":false,"removeByRestriction":false,"removeByWalking":false,"restriction":0,"stepsToRemove":100,"messageType":1},{"id":21,"autoRemovalTiming":2,"chanceByDamage":100,"traits":[{"code":23,"dataId":0,"value":0}],"iconIndex":81,"maxTurns":5,"message1":"%1你不易成为被狙击的目标！","message2":"","message3":"","message4":"","minTurns":5,"motion":0,"name":"隐蔽","note":"","overlay":0,"priority":40,"removeAtBattleEnd":true,"removeByDamage":false,"removeByRestriction":false,"removeByWalking":false,"restriction":0,"stepsToRemove":100,"messageType":1},{"id":22,"autoRemovalTiming":1,"chanceByDamage":100,"traits":[{"code":22,"dataId":6,"value":0.7}],"iconIndex":77,"maxTurns":3,"message1":"%1你采取了物理攻击的反击态势！","message2":"%1你采取了物理攻击的反击态势！","message3":"","message4":"%1敌人的反击状态解除了！","minTurns":3,"motion":0,"name":"反击","note":"","overlay":0,"priority":50,"removeAtBattleEnd":true,"removeByDamage":false,"removeByRestriction":true,"removeByWalking":false,"restriction":0,"stepsToRemove":100,"messageType":1},{"id":23,"autoRemovalTiming":2,"chanceByDamage":100,"traits":[{"code":14,"dataId":4,"value":1},{"code":14,"dataId":5,"value":1},{"code":14,"dataId":6,"value":1},{"code":14,"dataId":7,"value":1},{"code":14,"dataId":8,"value":1},{"code":14,"dataId":9,"value":1},{"code":14,"dataId":10,"value":1},{"code":14,"dataId":12,"value":1},{"code":14,"dataId":13,"value":1},{"code":14,"dataId":11,"value":1},{"code":14,"dataId":33,"value":1},{"code":14,"dataId":14,"value":1},{"code":14,"dataId":49,"value":1},{"code":14,"dataId":58,"value":1}],"iconIndex":93,"maxTurns":6,"message1":"%1你于数回合内防止了所有的异常状态！","message2":"%1你于数回合内防止了所有的异常状态！","message3":"","message4":"%1敌人的防止异常状态解除了！","minTurns":6,"motion":0,"name":"防止异常状态","note":"","overlay":0,"priority":50,"removeAtBattleEnd":true,"removeByDamage":false,"removeByRestriction":false,"removeByWalking":false,"restriction":0,"stepsToRemove":100,"messageType":1},{"id":24,"autoRemovalTiming":2,"chanceByDamage":100,"traits":[{"code":23,"dataId":4,"value":0.25}],"iconIndex":70,"maxTurns":5,"message1":"","message2":"","message3":"","message4":"","minTurns":5,"motion":0,"name":"减少消耗MP","note":"","overlay":0,"priority":50,"removeAtBattleEnd":true,"removeByDamage":false,"removeByRestriction":false,"removeByWalking":false,"restriction":0,"stepsToRemove":100,"messageType":1},{"id":25,"autoRemovalTiming":2,"chanceByDamage":100,"traits":[{"code":31,"dataId":2,"value":1},{"code":11,"dataId":2,"value":0.5},{"code":21,"dataId":2,"value":1.1}],"iconIndex":80,"maxTurns":5,"message1":"%1火焰的力量包覆了你的全身。","message2":"%1火焰的力量包覆了你的全身。","message3":"","message4":"","minTurns":5,"motion":0,"name":"火焰之力","note":"","overlay":0,"priority":50,"removeAtBattleEnd":true,"removeByDamage":false,"removeByRestriction":false,"removeByWalking":false,"restriction":0,"stepsToRemove":100,"messageType":1},{"id":26,"autoRemovalTiming":2,"chanceByDamage":100,"traits":[{"code":31,"dataId":3,"value":1},{"code":11,"dataId":3,"value":0.5},{"code":11,"dataId":5,"value":0.5},{"code":21,"dataId":2,"value":1.1}],"iconIndex":81,"maxTurns":5,"message1":"%1将冰的力量附着在身上。","message2":"%1将冰的力量附着在身上。","message3":"","message4":"","minTurns":5,"motion":0,"name":"冰的力量","note":"","overlay":0,"priority":50,"removeAtBattleEnd":true,"removeByDamage":false,"removeByRestriction":false,"removeByWalking":false,"restriction":0,"stepsToRemove":100,"messageType":1},{"id":27,"autoRemovalTiming":2,"chanceByDamage":100,"traits":[{"code":31,"dataId":4,"value":1},{"code":11,"dataId":4,"value":0.5},{"code":21,"dataId":2,"value":1.1}],"iconIndex":82,"maxTurns":5,"message1":"%1将雷的力量附着在身上。","message2":"%1将雷的力量附着在身上。","message3":"","message4":"","minTurns":5,"motion":0,"name":"雷的力量","note":"","overlay":0,"priority":50,"removeAtBattleEnd":true,"removeByDamage":false,"removeByRestriction":false,"removeByWalking":false,"restriction":0,"stepsToRemove":100,"messageType":1},{"id":28,"autoRemovalTiming":2,"chanceByDamage":100,"traits":[{"code":62,"dataId":0,"value":1}],"iconIndex":0,"maxTurns":1,"message1":"","message2":"","message3":"","message4":"","minTurns":1,"motion":0,"name":"◆自动","note":"","overlay":0,"priority":50,"removeAtBattleEnd":false,"removeByDamage":false,"removeByRestriction":false,"removeByWalking":false,"restriction":0,"stepsToRemove":100,"messageType":1},{"id":29,"autoRemovalTiming":0,"chanceByDamage":100,"traits":[{"code":64,"dataId":0,"value":1}],"iconIndex":72,"maxTurns":1,"message1":"","message2":"","message3":"","message4":"","minTurns":1,"motion":0,"name":"遇敌概率减半","note":"","overlay":0,"priority":20,"removeAtBattleEnd":false,"removeByDamage":false,"removeByRestriction":false,"removeByWalking":true,"restriction":0,"stepsToRemove":100,"messageType":1},{"id":30,"autoRemovalTiming":0,"chanceByDamage":100,"traits":[{"code":64,"dataId":4,"value":1},{"code":64,"dataId":5,"value":1}],"iconIndex":70,"maxTurns":1,"message1":"","message2":"","message3":"","message4":"","minTurns":1,"motion":0,"name":"赏金、道具2倍","note":"","overlay":0,"priority":20,"removeAtBattleEnd":false,"removeByDamage":false,"removeByRestriction":false,"removeByWalking":true,"restriction":0,"stepsToRemove":100,"messageType":1},{"id":31,"autoRemovalTiming":0,"chanceByDamage":100,"traits":[{"code":23,"dataId":9,"value":2}],"iconIndex":70,"maxTurns":1,"message1":"","message2":"","message3":"","message4":"","minTurns":1,"motion":0,"name":"经验值2倍。","note":"","overlay":0,"priority":20,"removeAtBattleEnd":false,"removeByDamage":false,"removeByRestriction":false,"removeByWalking":true,"restriction":0,"stepsToRemove":1,"messageType":1},{"id":32,"autoRemovalTiming":0,"chanceByDamage":100,"traits":[],"iconIndex":0,"maxTurns":1,"message1":"","message2":"","message3":"","message4":"","minTurns":1,"motion":0,"name":"","note":"","overlay":0,"priority":50,"removeAtBattleEnd":false,"removeByDamage":false,"removeByRestriction":false,"removeByWalking":false,"restriction":0,"stepsToRemove":100,"messageType":1},{"id":33,"autoRemovalTiming":2,"chanceByDamage":100,"iconIndex":64,"maxTurns":5,"message1":"%1受到了烧伤！","message2":"%1你让对方受到了烧伤！","message3":"","message4":"%1的烧伤消失了！","minTurns":2,"motion":1,"overlay":0,"name":"烧伤","note":"","priority":50,"releaseByDamage":false,"removeAtBattleEnd":true,"removeByDamage":false,"removeByRestriction":false,"removeByWalking":false,"restriction":0,"stepsToRemove":100,"traits":[{"code":22,"dataId":7,"value":-0.05}],"messageType":1},{"id":34,"autoRemovalTiming":0,"chanceByDamage":100,"iconIndex":27,"maxTurns":1,"message1":"%1你受到了药物中毒！","message2":"%1你让对方受到了药物中毒！","message3":"","message4":"%1的药物中毒消失了！","minTurns":1,"motion":1,"overlay":0,"name":"药物中毒(伪装)","note":"","priority":80,"releaseByDamage":false,"removeAtBattleEnd":false,"removeByDamage":false,"removeByRestriction":false,"removeByWalking":false,"restriction":0,"stepsToRemove":100,"traits":[{"code":21,"dataId":2,"value":0.5},{"code":21,"dataId":3,"value":0.5},{"code":21,"dataId":4,"value":0.5},{"code":21,"dataId":5,"value":0.5},{"code":21,"dataId":6,"value":0.5},{"code":21,"dataId":7,"value":0.5}],"messageType":1},{"id":35,"autoRemovalTiming":0,"chanceByDamage":100,"traits":[],"iconIndex":0,"maxTurns":1,"message1":"","message2":"","message3":"","message4":"","minTurns":1,"motion":0,"name":"","note":"","overlay":0,"priority":50,"removeAtBattleEnd":false,"removeByDamage":false,"removeByRestriction":false,"removeByWalking":false,"restriction":0,"stepsToRemove":100,"messageType":1},{"id":36,"autoRemovalTiming":2,"chanceByDamage":100,"traits":[{"code":21,"dataId":2,"value":1.2},{"code":21,"dataId":3,"value":1.2},{"code":21,"dataId":4,"value":1.2},{"code":21,"dataId":5,"value":1.2},{"code":21,"dataId":6,"value":1.2},{"code":21,"dataId":7,"value":1.2},{"code":22,"dataId":9,"value":0.05}],"iconIndex":1979,"maxTurns":6,"message1":"%1女武神的加护寄宿在你身上！","message2":"%1女武神的加护寄宿在你身上！","message3":"","message4":"%1女武神的加护从你身上消失了！","minTurns":6,"motion":0,"name":"女武神","note":"","overlay":0,"priority":80,"removeAtBattleEnd":true,"removeByDamage":false,"removeByRestriction":false,"removeByWalking":false,"restriction":0,"stepsToRemove":100,"messageType":1},{"id":37,"autoRemovalTiming":2,"chanceByDamage":100,"traits":[{"code":21,"dataId":2,"value":1.5},{"code":21,"dataId":3,"value":1.5},{"code":21,"dataId":4,"value":1.5},{"code":21,"dataId":5,"value":1.5},{"code":21,"dataId":6,"value":1.5},{"code":21,"dataId":7,"value":1.5},{"code":22,"dataId":9,"value":0.1}],"iconIndex":1981,"maxTurns":6,"message1":"%1神之力寄宿在你身上！","message2":"%1神之力寄宿在你身上！","message3":"","message4":"%1神之力从你身上消失了！","minTurns":6,"motion":0,"name":"神之力","note":"","overlay":0,"priority":80,"removeAtBattleEnd":true,"removeByDamage":false,"removeByRestriction":false,"removeByWalking":false,"restriction":0,"stepsToRemove":100,"messageType":1},{"id":38,"autoRemovalTiming":0,"chanceByDamage":100,"traits":[],"iconIndex":0,"maxTurns":1,"message1":"","message2":"","message3":"","message4":"","minTurns":1,"motion":0,"name":"","note":"","overlay":0,"priority":50,"removeAtBattleEnd":false,"removeByDamage":false,"removeByRestriction":false,"removeByWalking":false,"restriction":0,"stepsToRemove":100,"messageType":1},{"id":39,"autoRemovalTiming":1,"chanceByDamage":100,"iconIndex":18,"maxTurns":5,"message1":"%1你受到了食物中毒！","message2":"%1你让对方受到了食物中毒！","message3":"","message4":"%1食物中毒消失了！","minTurns":3,"motion":1,"overlay":0,"name":"食物中毒","note":"","priority":60,"releaseByDamage":false,"removeAtBattleEnd":false,"removeByDamage":false,"removeByRestriction":false,"removeByWalking":false,"restriction":0,"stepsToRemove":100,"traits":[{"code":21,"dataId":2,"value":0.8},{"code":21,"dataId":3,"value":0.8},{"code":21,"dataId":4,"value":0.8},{"code":21,"dataId":5,"value":0.8},{"code":21,"dataId":6,"value":0.8},{"code":21,"dataId":7,"value":0.8}],"messageType":1},{"id":40,"autoRemovalTiming":0,"chanceByDamage":100,"iconIndex":1102,"maxTurns":1,"message1":"%1你受到了药物中毒！","message2":"%1你让对方受到了药物中毒！","message3":"","message4":"%1的药物中毒消失了！","minTurns":1,"motion":1,"overlay":0,"name":"药物中毒","note":"<永续状态持续中>","priority":80,"releaseByDamage":false,"removeAtBattleEnd":false,"removeByDamage":false,"removeByRestriction":false,"removeByWalking":false,"restriction":0,"stepsToRemove":100,"traits":[{"code":21,"dataId":2,"value":0.5},{"code":21,"dataId":3,"value":0.5},{"code":21,"dataId":4,"value":0.5},{"code":21,"dataId":5,"value":0.5},{"code":21,"dataId":6,"value":0.5},{"code":21,"dataId":7,"value":0.5}],"messageType":1},{"id":41,"autoRemovalTiming":0,"chanceByDamage":100,"iconIndex":3152,"maxTurns":1,"message1":"","message2":"","message3":"","message4":"","minTurns":1,"motion":1,"overlay":0,"name":"奴隶纹","note":"<永续状态持续中>","priority":1,"releaseByDamage":false,"removeAtBattleEnd":false,"removeByDamage":false,"removeByRestriction":false,"removeByWalking":false,"restriction":0,"stepsToRemove":100,"traits":[{"code":21,"dataId":0,"value":0.1},{"code":21,"dataId":1,"value":0.1},{"code":21,"dataId":2,"value":0.1},{"code":21,"dataId":3,"value":0.1},{"code":21,"dataId":4,"value":0.1},{"code":21,"dataId":5,"value":0.1},{"code":21,"dataId":6,"value":0.1},{"code":21,"dataId":7,"value":0.1}],"messageType":1},{"id":42,"autoRemovalTiming":2,"chanceByDamage":100,"iconIndex":27,"maxTurns":3,"message1":"","message2":"","message3":"","message4":"%1从无力状态恢复！","minTurns":3,"motion":1,"overlay":0,"name":"无力","note":"","priority":1,"releaseByDamage":false,"removeAtBattleEnd":false,"removeByDamage":false,"removeByRestriction":false,"removeByWalking":false,"restriction":0,"stepsToRemove":100,"traits":[{"code":21,"dataId":2,"value":0.5},{"code":21,"dataId":3,"value":0.5},{"code":21,"dataId":4,"value":0.5},{"code":21,"dataId":5,"value":0.5},{"code":21,"dataId":6,"value":0.5},{"code":21,"dataId":7,"value":0.5}],"messageType":1},{"id":43,"autoRemovalTiming":0,"chanceByDamage":100,"traits":[],"iconIndex":0,"maxTurns":1,"message1":"","message2":"","message3":"","message4":"","minTurns":1,"motion":0,"name":"","note":"","overlay":0,"priority":50,"removeAtBattleEnd":false,"removeByDamage":false,"removeByRestriction":false,"removeByWalking":false,"restriction":0,"stepsToRemove":100,"messageType":1},{"id":44,"autoRemovalTiming":0,"chanceByDamage":100,"traits":[],"iconIndex":0,"maxTurns":1,"message1":"","message2":"","message3":"","message4":"","minTurns":1,"motion":0,"name":"精液满身","note":"<永续状态持续中>","overlay":0,"priority":0,"removeAtBattleEnd":false,"removeByDamage":false,"removeByRestriction":false,"removeByWalking":false,"restriction":0,"stepsToRemove":100,"messageType":1},{"id":45,"autoRemovalTiming":0,"chanceByDamage":100,"traits":[],"iconIndex":0,"maxTurns":1,"message1":"","message2":"","message3":"","message4":"","minTurns":1,"motion":0,"name":"肥大腹部","note":"<永续状态持续中>","overlay":0,"priority":0,"removeAtBattleEnd":false,"removeByDamage":false,"removeByRestriction":false,"removeByWalking":false,"restriction":0,"stepsToRemove":100,"messageType":1},{"id":46,"autoRemovalTiming":0,"chanceByDamage":100,"traits":[],"iconIndex":0,"maxTurns":1,"message1":"","message2":"","message3":"","message4":"","minTurns":1,"motion":0,"name":"恶心乳头化","note":"<永续状态持续中>","overlay":0,"priority":0,"removeAtBattleEnd":false,"removeByDamage":false,"removeByRestriction":false,"removeByWalking":false,"restriction":0,"stepsToRemove":100,"messageType":1},{"id":47,"autoRemovalTiming":0,"chanceByDamage":100,"traits":[],"iconIndex":0,"maxTurns":1,"message1":"","message2":"","message3":"","message4":"","minTurns":1,"motion":0,"name":"","note":"","overlay":0,"priority":50,"removeAtBattleEnd":false,"removeByDamage":false,"removeByRestriction":false,"removeByWalking":false,"restriction":0,"stepsToRemove":100,"messageType":1},{"id":48,"autoRemovalTiming":2,"chanceByDamage":100,"traits":[{"code":23,"dataId":6,"value":0},{"code":23,"dataId":7,"value":0},{"code":62,"dataId":1,"value":1},{"code":11,"dataId":1,"value":0},{"code":11,"dataId":2,"value":0},{"code":11,"dataId":3,"value":0},{"code":11,"dataId":4,"value":0},{"code":11,"dataId":5,"value":0},{"code":11,"dataId":6,"value":0},{"code":11,"dataId":7,"value":0},{"code":11,"dataId":8,"value":0},{"code":11,"dataId":9,"value":0},{"code":21,"dataId":3,"value":10},{"code":21,"dataId":5,"value":10},{"code":14,"dataId":4,"value":1},{"code":14,"dataId":5,"value":1},{"code":14,"dataId":6,"value":1},{"code":14,"dataId":7,"value":1},{"code":14,"dataId":8,"value":1},{"code":14,"dataId":9,"value":1},{"code":14,"dataId":10,"value":1},{"code":14,"dataId":12,"value":1},{"code":14,"dataId":13,"value":1},{"code":14,"dataId":11,"value":1},{"code":14,"dataId":33,"value":1},{"code":14,"dataId":14,"value":1},{"code":14,"dataId":49,"value":1},{"code":14,"dataId":58,"value":1}],"iconIndex":93,"maxTurns":1,"message1":"","message2":"","message3":"","message4":"","minTurns":1,"motion":0,"name":"完全防御","note":"","overlay":0,"priority":40,"removeAtBattleEnd":true,"removeByDamage":false,"removeByRestriction":false,"removeByWalking":false,"restriction":0,"stepsToRemove":100,"messageType":1},{"id":49,"autoRemovalTiming":1,"chanceByDamage":20,"iconIndex":2503,"maxTurns":4,"message1":"%1被催眠了！","message2":"%1使对象陷入催眠状态！","message3":"","message4":"%1从催眠中清醒了！","minTurns":2,"motion":1,"name":"催眠","note":"","overlay":0,"priority":80,"releaseByDamage":false,"removeAtBattleEnd":true,"removeByDamage":true,"removeByRestriction":false,"removeByWalking":false,"restriction":4,"stepsToRemove":100,"traits":[{"code":21,"dataId":2,"value":0},{"code":21,"dataId":3,"value":0.5},{"code":21,"dataId":5,"value":0.5}],"messageType":1},{"id":50,"autoRemovalTiming":1,"chanceByDamage":50,"iconIndex":2503,"maxTurns":5,"message1":"%1被催眠了！","message2":"%1使对象陷入催眠状态！","message3":"","message4":"%1从催眠中清醒了！","minTurns":3,"motion":1,"name":"催眠(事件)","note":"","overlay":0,"priority":80,"releaseByDamage":false,"removeAtBattleEnd":true,"removeByDamage":false,"removeByRestriction":false,"removeByWalking":false,"restriction":4,"stepsToRemove":100,"traits":[{"code":42,"dataId":1,"value":1},{"code":42,"dataId":2,"value":1},{"code":21,"dataId":2,"value":0},{"code":21,"dataId":3,"value":0.5},{"code":21,"dataId":5,"value":0.5}],"messageType":1},{"id":51,"autoRemovalTiming":0,"chanceByDamage":100,"traits":[],"iconIndex":0,"maxTurns":1,"message1":"","message2":"","message3":"","message4":"","minTurns":1,"motion":0,"name":"","note":"","overlay":0,"priority":50,"removeAtBattleEnd":false,"removeByDamage":false,"removeByRestriction":false,"removeByWalking":false,"restriction":0,"stepsToRemove":100,"messageType":1},{"id":52,"autoRemovalTiming":2,"chanceByDamage":100,"traits":[{"code":21,"dataId":2,"value":1.5},{"code":21,"dataId":4,"value":1.5},{"code":62,"dataId":0,"value":1}],"iconIndex":3106,"maxTurns":5,"message1":"%1使对象陷入兴奋状态！","message2":"%1使对象陷入兴奋状态！","message3":"","message4":"","minTurns":5,"motion":0,"name":"兴奋","note":"","overlay":0,"priority":50,"removeAtBattleEnd":true,"removeByDamage":false,"removeByRestriction":false,"removeByWalking":false,"restriction":0,"stepsToRemove":100,"messageType":1},{"id":53,"autoRemovalTiming":2,"chanceByDamage":100,"traits":[{"code":61,"dataId":0,"value":1}],"iconIndex":3058,"maxTurns":3,"message1":"%1从现在开始三回合，可进行两次行动！","message2":"%1从现在开始三回合，进行两次行动！","message3":"%1正在二轮行动中！","message4":"%1的二轮行动结束了！","minTurns":3,"motion":0,"name":"二轮行动","note":"","overlay":0,"priority":40,"removeAtBattleEnd":true,"removeByDamage":false,"removeByRestriction":false,"removeByWalking":false,"restriction":0,"stepsToRemove":100,"messageType":1},{"id":54,"autoRemovalTiming":0,"chanceByDamage":100,"traits":[],"iconIndex":0,"maxTurns":1,"message1":"","message2":"","message3":"","message4":"","minTurns":1,"motion":0,"name":"","note":"","overlay":0,"priority":50,"removeAtBattleEnd":false,"removeByDamage":false,"removeByRestriction":false,"removeByWalking":false,"restriction":0,"stepsToRemove":100,"messageType":1},{"id":55,"autoRemovalTiming":0,"chanceByDamage":100,"traits":[],"iconIndex":228,"maxTurns":6,"message1":"%1战斗不能时，自动复活！","message2":"","message3":"","message4":"","minTurns":6,"motion":0,"name":"自动复活","note":"<暂时自动苏生>\n<蘇生HPレート:30>","overlay":0,"priority":60,"removeAtBattleEnd":true,"removeByDamage":false,"removeByRestriction":false,"removeByWalking":false,"restriction":0,"stepsToRemove":100,"messageType":1},{"id":56,"autoRemovalTiming":0,"chanceByDamage":100,"traits":[],"iconIndex":228,"maxTurns":6,"message1":"%1战斗不能时，自动复活！","message2":"","message3":"","message4":"","minTurns":6,"motion":0,"name":"不死鸟之护","note":"〈暂时自动苏生〉\n<蘇生HPレート:100>","overlay":0,"priority":60,"removeAtBattleEnd":true,"removeByDamage":false,"removeByRestriction":false,"removeByWalking":false,"restriction":0,"stepsToRemove":100,"messageType":1},{"id":57,"autoRemovalTiming":2,"chanceByDamage":100,"traits":[{"code":21,"dataId":2,"value":0.8},{"code":21,"dataId":3,"value":0.8},{"code":21,"dataId":4,"value":0.8},{"code":21,"dataId":5,"value":0.8}],"iconIndex":3079,"maxTurns":6,"message1":"%1已遭受天谴！全能力值降低20％！","message2":"%1已遭受天谴！全能力值降低20％！","message3":"","message4":"%1已从天谴状态恢复！","minTurns":4,"motion":0,"name":"天谴","note":"","overlay":0,"priority":60,"removeAtBattleEnd":true,"removeByDamage":false,"removeByRestriction":false,"removeByWalking":false,"restriction":0,"stepsToRemove":100,"messageType":1},{"id":58,"autoRemovalTiming":2,"chanceByDamage":100,"traits":[{"code":11,"dataId":2,"value":1.5},{"code":11,"dataId":3,"value":1.5},{"code":11,"dataId":5,"value":1.5},{"code":11,"dataId":6,"value":1.5},{"code":11,"dataId":7,"value":1.5}],"iconIndex":3089,"maxTurns":6,"message1":"","message2":"","message3":"","message4":"","minTurns":6,"motion":0,"name":"四元减少","note":"","overlay":0,"priority":60,"removeAtBattleEnd":true,"removeByDamage":false,"removeByRestriction":false,"removeByWalking":false,"restriction":0,"stepsToRemove":100,"messageType":1},{"id":59,"autoRemovalTiming":0,"chanceByDamage":100,"traits":[],"iconIndex":0,"maxTurns":1,"message1":"","message2":"","message3":"","message4":"","minTurns":1,"motion":0,"name":"","note":"","overlay":0,"priority":50,"removeAtBattleEnd":false,"removeByDamage":false,"removeByRestriction":false,"removeByWalking":false,"restriction":0,"stepsToRemove":100,"messageType":1},{"id":60,"autoRemovalTiming":0,"chanceByDamage":100,"traits":[{"code":21,"dataId":0,"value":2},{"code":21,"dataId":1,"value":2},{"code":21,"dataId":2,"value":2},{"code":21,"dataId":3,"value":2},{"code":21,"dataId":4,"value":2},{"code":21,"dataId":5,"value":2},{"code":21,"dataId":6,"value":2},{"code":21,"dataId":7,"value":2}],"iconIndex":0,"maxTurns":1,"message1":"","message2":"","message3":"","message4":"","minTurns":1,"motion":0,"name":"倍增","note":"","overlay":0,"priority":50,"removeAtBattleEnd":false,"removeByDamage":false,"removeByRestriction":false,"removeByWalking":false,"restriction":0,"stepsToRemove":100,"messageType":1},{"id":61,"autoRemovalTiming":2,"chanceByDamage":100,"traits":[{"code":22,"dataId":2,"value":1}],"iconIndex":90,"maxTurns":6,"message1":"","message2":"","message3":"","message4":"","minTurns":6,"motion":0,"name":"会心","note":"","overlay":0,"priority":50,"removeAtBattleEnd":true,"removeByDamage":false,"removeByRestriction":false,"removeByWalking":false,"restriction":0,"stepsToRemove":100,"messageType":1},{"id":62,"autoRemovalTiming":0,"chanceByDamage":100,"traits":[{"code":41,"dataId":1,"value":1}],"iconIndex":11,"maxTurns":1,"message1":"","message2":"","message3":"","message4":"","minTurns":1,"motion":0,"name":"封印解除","note":"","overlay":0,"priority":50,"removeAtBattleEnd":true,"removeByDamage":false,"removeByRestriction":false,"removeByWalking":false,"restriction":0,"stepsToRemove":100,"messageType":1},{"id":63,"autoRemovalTiming":0,"chanceByDamage":100,"traits":[],"iconIndex":0,"maxTurns":1,"message1":"","message2":"","message3":"","message4":"","minTurns":1,"motion":0,"name":"","note":"","overlay":0,"priority":50,"removeAtBattleEnd":false,"removeByDamage":false,"removeByRestriction":false,"removeByWalking":false,"restriction":0,"stepsToRemove":100,"messageType":1},{"id":64,"autoRemovalTiming":1,"chanceByDamage":100,"traits":[{"code":22,"dataId":6,"value":1}],"iconIndex":77,"maxTurns":1,"message1":"%1已遭受反击状态！","message2":"%1已遭受反击状态！","message3":"","message4":"%1敌人的反击状态解除了！","minTurns":1,"motion":0,"name":"反击","note":"","overlay":0,"priority":50,"removeAtBattleEnd":true,"removeByDamage":false,"removeByRestriction":true,"removeByWalking":false,"restriction":0,"stepsToRemove":100,"messageType":1},{"id":65,"autoRemovalTiming":2,"chanceByDamage":100,"traits":[{"code":22,"dataId":1,"value":-1},{"code":23,"dataId":5,"value":0}],"iconIndex":1215,"maxTurns":3,"message1":"%1已遭受雪人状态！","message2":"%1已遭受雪人状态！","message3":"%1雪人状态无法累积TP！","message4":"%1雪人状态解除！","minTurns":2,"motion":1,"name":"雪人","note":"无法解除","overlay":0,"priority":90,"removeAtBattleEnd":true,"removeByDamage":false,"removeByRestriction":false,"removeByWalking":false,"restriction":0,"stepsToRemove":100,"messageType":1},{"id":66,"autoRemovalTiming":2,"chanceByDamage":100,"traits":[{"code":11,"dataId":2,"value":0.5},{"code":11,"dataId":3,"value":0.5},{"code":11,"dataId":5,"value":0.5},{"code":11,"dataId":6,"value":0.5},{"code":11,"dataId":7,"value":0.5}],"iconIndex":3088,"maxTurns":6,"message1":"","message2":"","message3":"","message4":"","minTurns":6,"motion":0,"name":"四元抗性","note":"无法解除","overlay":0,"priority":60,"removeAtBattleEnd":true,"removeByDamage":false,"removeByRestriction":false,"removeByWalking":false,"restriction":0,"stepsToRemove":100,"messageType":1},{"id":67,"autoRemovalTiming":1,"chanceByDamage":100,"iconIndex":3075,"maxTurns":3,"message1":"%1已遭受防御破坏状态！","message2":"%1已让对象防御破坏状态！","message3":"","message4":"%1已让对象恢复原本的防御破坏状态！","minTurns":2,"motion":1,"name":"防御破坏","note":"","overlay":0,"priority":60,"releaseByDamage":false,"removeAtBattleEnd":true,"removeByDamage":false,"removeByRestriction":false,"removeByWalking":false,"restriction":0,"stepsToRemove":100,"traits":[{"code":21,"dataId":3,"value":0}],"messageType":1},{"id":68,"autoRemovalTiming":2,"chanceByDamage":100,"traits":[{"code":21,"dataId":3,"value":5},{"code":21,"dataId":5,"value":5}],"iconIndex":171,"maxTurns":6,"message1":"","message2":"","message3":"","message4":"%1铁壁状态解除！","minTurns":6,"motion":0,"name":"铁壁","note":"","overlay":0,"priority":50,"removeAtBattleEnd":true,"removeByDamage":false,"removeByRestriction":false,"removeByWalking":false,"restriction":0,"stepsToRemove":100,"messageType":1},{"id":69,"autoRemovalTiming":0,"chanceByDamage":100,"traits":[{"code":61,"dataId":0,"value":1}],"iconIndex":0,"maxTurns":6,"message1":"","message2":"","message3":"","message4":"","minTurns":6,"motion":0,"name":"三回行动","note":"","overlay":0,"priority":50,"removeAtBattleEnd":true,"removeByDamage":false,"removeByRestriction":false,"removeByWalking":false,"restriction":0,"stepsToRemove":100,"messageType":1},{"id":70,"autoRemovalTiming":0,"chanceByDamage":100,"traits":[{"code":21,"dataId":0,"value":2},{"code":21,"dataId":1,"value":2},{"code":21,"dataId":2,"value":2},{"code":21,"dataId":3,"value":2},{"code":21,"dataId":4,"value":2},{"code":21,"dataId":5,"value":2},{"code":21,"dataId":6,"value":2},{"code":21,"dataId":7,"value":2}],"iconIndex":0,"maxTurns":1,"message1":"","message2":"","message3":"","message4":"","minTurns":1,"motion":0,"name":"易容","note":"<永续状态持续中>","overlay":0,"priority":50,"removeAtBattleEnd":false,"removeByDamage":false,"removeByRestriction":false,"removeByWalking":false,"restriction":0,"stepsToRemove":100,"messageType":1},{"id":71,"autoRemovalTiming":0,"chanceByDamage":100,"traits":[{"code":23,"dataId":6,"value":0},{"code":23,"dataId":7,"value":0},{"code":11,"dataId":1,"value":0},{"code":11,"dataId":2,"value":0},{"code":11,"dataId":3,"value":0},{"code":11,"dataId":4,"value":0},{"code":11,"dataId":5,"value":0},{"code":11,"dataId":6,"value":0},{"code":11,"dataId":7,"value":0},{"code":11,"dataId":8,"value":0},{"code":11,"dataId":9,"value":0},{"code":11,"dataId":13,"value":0},{"code":14,"dataId":1,"value":1},{"code":14,"dataId":4,"value":1},{"code":14,"dataId":5,"value":1},{"code":14,"dataId":6,"value":1},{"code":14,"dataId":7,"value":1},{"code":14,"dataId":8,"value":1},{"code":14,"dataId":9,"value":1},{"code":14,"dataId":10,"value":1},{"code":14,"dataId":12,"value":1},{"code":14,"dataId":13,"value":1},{"code":14,"dataId":11,"value":1},{"code":14,"dataId":33,"value":1},{"code":14,"dataId":14,"value":1},{"code":14,"dataId":49,"value":1},{"code":14,"dataId":58,"value":1},{"code":14,"dataId":65,"value":1},{"code":14,"dataId":67,"value":1},{"code":21,"dataId":2,"value":5},{"code":21,"dataId":3,"value":5},{"code":21,"dataId":4,"value":5},{"code":21,"dataId":5,"value":5},{"code":21,"dataId":6,"value":5},{"code":21,"dataId":7,"value":5}],"iconIndex":0,"maxTurns":1,"message1":"","message2":"","message3":"","message4":"","minTurns":1,"motion":0,"name":"最强","note":"","overlay":0,"priority":0,"removeAtBattleEnd":false,"removeByDamage":false,"removeByRestriction":false,"removeByWalking":false,"restriction":0,"stepsToRemove":100,"messageType":1}]